buflow/__init__.py
buflow/task.py
buflow-1.0.0.dist-info/LICENSE
buflow-1.0.0.dist-info/METADATA
buflow-1.0.0.dist-info/WHEEL
buflow-1.0.0.dist-info/top_level.txt
buflow-1.0.0.dist-info/RECORD
